jl_hidecode/__init__.py
jl_hidecode/_version.py
jl_hidecode/labextension/package.json
jl_hidecode/labextension/schemas/jl-hidecode/package.json.orig
jl_hidecode/labextension/schemas/jl-hidecode/plugin.json
jl_hidecode/labextension/static/509.8f1332aca76043442750.js
jl_hidecode/labextension/static/728.079f6b1790efc8718630.js
jl_hidecode/labextension/static/remoteEntry.3757abf8668caec0a288.js
jl_hidecode/labextension/static/style.js
jl_hidecode/labextension/static/third-party-licenses.json
jl_hidecode-0.0.1.data/data/share/jupyter/labextensions/jl-hidecode/package.json
jl_hidecode-0.0.1.data/data/share/jupyter/labextensions/jl-hidecode/schemas/jl-hidecode/package.json.orig
jl_hidecode-0.0.1.data/data/share/jupyter/labextensions/jl-hidecode/schemas/jl-hidecode/plugin.json
jl_hidecode-0.0.1.data/data/share/jupyter/labextensions/jl-hidecode/static/509.8f1332aca76043442750.js
jl_hidecode-0.0.1.data/data/share/jupyter/labextensions/jl-hidecode/static/728.079f6b1790efc8718630.js
jl_hidecode-0.0.1.data/data/share/jupyter/labextensions/jl-hidecode/static/remoteEntry.3757abf8668caec0a288.js
jl_hidecode-0.0.1.data/data/share/jupyter/labextensions/jl-hidecode/static/style.js
jl_hidecode-0.0.1.data/data/share/jupyter/labextensions/jl-hidecode/static/third-party-licenses.json
jl_hidecode-0.0.1.data/data/share/jupyter/labextensions/jl-hidecode/install.json
jl_hidecode-0.0.1.dist-info/METADATA
jl_hidecode-0.0.1.dist-info/WHEEL
jl_hidecode-0.0.1.dist-info/licenses/LICENSE
jl_hidecode-0.0.1.dist-info/RECORD
