Metadata-Version: 2.4
Name: jl-hidecode
Version: 0.0.1
Dynamic: Keywords
Summary: Hide/show notebook inputs with a Colab-like play button parameter widgets in JupyterLab.
Project-URL: Homepage, https://github.com/CellMigrationLab/jl-hidecode
Project-URL: Bug Tracker, https://github.com/CellMigrationLab/jl-hidecode/issues
Project-URL: Repository, https://github.com/CellMigrationLab/jl-hidecode.git
Author-email: CellMigrationLab <jacquemetlab@gmail.com>
License: BSD 3-Clause License
License-File: LICENSE
Classifier: Framework :: Jupyter
Classifier: Framework :: Jupyter :: JupyterLab
Classifier: Framework :: Jupyter :: JupyterLab :: 4
Classifier: Framework :: Jupyter :: JupyterLab :: Extensions
Classifier: Framework :: Jupyter :: JupyterLab :: Extensions :: Prebuilt
Classifier: License :: OSI Approved :: BSD License
Classifier: Programming Language :: Python
Classifier: Programming Language :: Python :: 3
Classifier: Programming Language :: Python :: 3.8
Classifier: Programming Language :: Python :: 3.9
Classifier: Programming Language :: Python :: 3.10
Classifier: Programming Language :: Python :: 3.11
Requires-Python: >=3.8
